LICENCE.txt
MANIFEST.in
README.rst
setup.py
django_html5_appcache.egg-info/PKG-INFO
django_html5_appcache.egg-info/SOURCES.txt
django_html5_appcache.egg-info/dependency_links.txt
django_html5_appcache.egg-info/not-zip-safe
django_html5_appcache.egg-info/requires.txt
django_html5_appcache.egg-info/top_level.txt
html5_appcache/__init__.py
html5_appcache/appcache_base.py
html5_appcache/cache.py
html5_appcache/models.py
html5_appcache/settings.py
html5_appcache/urls.py
html5_appcache/utils.py
html5_appcache/views.py
html5_appcache/management/__init__.py
html5_appcache/management/commands/__init__.py
html5_appcache/management/commands/clear_manifest.py
html5_appcache/management/commands/update_manifest.py
html5_appcache/middleware/__init__.py
html5_appcache/middleware/appcache_middleware.py
html5_appcache/migrations/0001_initial.py
html5_appcache/migrations/0002_permissions_data.py
html5_appcache/migrations/__init__.py
html5_appcache/packages/__init__.py
html5_appcache/packages/cms/__init__.py
html5_appcache/packages/cms/appcache.py
html5_appcache/packages/cms/models.py
html5_appcache/packages/cmsplugin_filer/__init__.py
html5_appcache/packages/cmsplugin_filer/appcache.py
html5_appcache/packages/cmsplugin_filer/models.py
html5_appcache/packages/filer/__init__.py
html5_appcache/packages/filer/appcache.py
html5_appcache/packages/filer/models.py
html5_appcache/static/img/html5_appcache_clean.png
html5_appcache/static/img/html5_appcache_dirty.png
html5_appcache/templates/html5_appcache/manifest
html5_appcache/templates/html5_appcache/templatetags/icon.html
html5_appcache/templatetags/__init__.py
html5_appcache/templatetags/appcache_tags.py
html5_appcache/test_utils/__init__.py
html5_appcache/test_utils/base.py
html5_appcache/test_utils/testapp/__init__.py
html5_appcache/test_utils/testapp/appcache.py
html5_appcache/test_utils/testapp/models.py
html5_appcache/test_utils/testapp/sitemap.py
html5_appcache/test_utils/testapp/urls.py
html5_appcache/test_utils/testapp/urls_23.py
html5_appcache/test_utils/testapp/views.py
html5_appcache/test_utils/testapp/templates/base.html
html5_appcache/test_utils/testapp/templates/testapp/news_detail.html
html5_appcache/test_utils/testapp/templates/testapp/news_list.html
html5_appcache/tests/__init__.py
