Metadata-Version: 1.1
Name: django-html5-appcache
Version: 0.3.1
Summary: HTML5 AppCache manifest generator
Home-page: http://www.nephila.it
Author: Iacopo Spalletti
Author-email: info@nephila.it
License: BSD License
Download-URL: https://github.com/nephila/django-html5-appcache
Platform: OS Independent
Classifier: Development Status :: 2 - Pre-Alpha
Classifier: Environment :: Web Environment
Classifier: Framework :: Django
Classifier: Intended Audience :: Developers
Classifier: License :: OSI Approved :: BSD License
Classifier: Operating System :: OS Independent
Classifier: Programming Language :: Python
Classifier: Topic :: Software Development
Classifier: Topic :: Software Development :: Libraries :: Python Modules
Classifier: Topic :: Internet :: WWW/HTTP :: Site Management
